netbox_licences/__init__.py
netbox_licences/admin.py
netbox_licences/filters.py
netbox_licences/forms.py
netbox_licences/models.py
netbox_licences/navigation.py
netbox_licences/tables.py
netbox_licences/urls.py
netbox_licences/views.py
netbox_licences/api/serializers.py
netbox_licences/api/urls.py
netbox_licences/api/views.py
netbox_licences/migrations/001_base_initial.py
netbox_licences/migrations/__init__.py
netbox_licences/templates/netbox_licences/licences_list.html
netbox_licences/templates/netbox_licences/software_providers_list.html
netbox_licences-0.1.3.dist-info/LICENSE.txt
netbox_licences-0.1.3.dist-info/METADATA
netbox_licences-0.1.3.dist-info/WHEEL
netbox_licences-0.1.3.dist-info/top_level.txt
netbox_licences-0.1.3.dist-info/RECORD
